LICENSE
MANIFEST.in
README.rst
setup.cfg
setup.py
im_api_clients/__init__.py
im_api_clients/hyperledger.py
im_api_clients.egg-info/PKG-INFO
im_api_clients.egg-info/SOURCES.txt
im_api_clients.egg-info/dependency_links.txt
im_api_clients.egg-info/top_level.txt