Metadata-Version: 1.1
Name: im-api-clients
Version: 0.6.0
Summary: A simple client for Inmediate REST API.
Home-page: https://github.com/ej2015/im_rest_client_python
Author: Edgar Ji
Author-email: edgar.ji@insurancemarket.sg
License: BSD License
Platform: UNKNOWN
Classifier: Intended Audience :: Developers
Classifier: License :: OSI Approved :: BSD License
Classifier: Operating System :: OS Independent
Classifier: Programming Language :: Python :: 3.5
Classifier: Programming Language :: Python :: 3.6
Classifier: Topic :: Internet :: WWW/HTTP
